[{"id":"110","image": "https://shtrlnk.ml/jdgSkdxRi3","desc":"BCOM V","year":"NOV 2019","name":"Business Economics - V"},{"id":"108","image": "https://shtrlnk.ml/YnqAeopOnQ","desc":"BCOM V","year":"NOV 2019","name":"Commerce - V"},{"id":"111","image": "https://shtrlnk.ml/KLT8zKVPMy","desc":"BCOM V","year":"NOV 2019","name":"Computer Systems & Applications Paper-I"},{"id":"109","image": "https://shtrlnk.ml/4yXTFOpktI","desc":"BCOM V","year":"NOV 2019","name":"Direct & Indirect Taxation Paper-I"},{"id":"188","image": "https://shtrlnk.ml/nY48byz7aW","desc":"BCOM V","year":"NOV 2019","name":"Elements of Operational Research Paper- I"},{"id":"107","image": "https://shtrlnk.ml/3Wr396j62v","desc":"BCOM V","year":"NOV 2019","name":"Export Marketing Paper-I"},{"id":"112","image": "https://shtrlnk.ml/BCcRkeyNcI","desc":"BCOM V","year":"NOV 2019","name":"Financial Accounting and Auditing VII - Financial Accounting"},{"id":"113","image": "https://shtrlnk.ml/twV3qZIpL1","desc":"BCOM V","year":"NOV 2019","name":"Financial Accounting and Auditing VIII - Cost Accounting"},{"id":"191","image": "https://shtrlnk.ml/cR1UUBooyZ","desc":"BCOM V","year":"NOV 2019","name":"Psychology of Human Behavior at Work Paper - I"}]